netplan/__init__.py
netplan/config.py
netplan/interface.py
netplan/parser.py
netplan/py.typed
netplan-0.3.3.data/scripts/netplan-parser
netplan-0.3.3.dist-info/METADATA
netplan-0.3.3.dist-info/WHEEL
netplan-0.3.3.dist-info/top_level.txt
netplan-0.3.3.dist-info/zip-safe
netplan-0.3.3.dist-info/RECORD
