Metadata-Version: 2.1
Name: netplan
Version: 0.3.3
Summary: A library for parsing the netplan configuration data
Home-page: https://github.com/storpool/netplan
Author: StorPool OpenStack development team
Author-email: openstack-dev@storpool.com
License: Apache License 2.0
Keywords: netplan
Platform: UNKNOWN
